{
  "ComponentIndexes": {},
  "ControlUniqueGuids": {},
  "ControlUniqueIds": {
    "App": 1,
    "Screen1": 3,
    "Screen2": 4
  },
  "FunctionParamsInvariantScripts": {},
  "FunctionParamsInvariantScriptsOnInstances": {},
  "HeaderLastSavedDateTimeUTC": "08/20/2022 06:09:09",
  "IsLegacyComponentAllowGlobalScopeCase": false,
  "LocalConnectionIDReferences": {},
  "LocalDatabaseReferencesAsEmpty": false,
  "LocalResourceFileNames": {},
  "LocalResourceRootPaths": {},
  "OrderComponentMetadata": {},
  "OrderComponentTemplate": {},
  "OrderDataSource": {},
  "OrderGroupControls": {},
  "OrderPcfTemplate": {},
  "OrderTemplate": {},
  "OrderXMLTemplate": {},
  "PublishOrderIndices": {
    "App": 0,
    "Screen1": 2,
    "Screen2": 3
  },
  "ResourcesJsonIndices": {},
  "RuleScreenIdWithoutScreen": {},
  "TemplateVersions": {},
  "VolatileProperties": {
    "AnalysisLoadTime": 0.0164127,
    "ControlCount": {
      "label": 1,
      "screen": 2
    },
    "DeserializationLoadTime": 0.1156284,
    "ErrorCount": 0
  },
  "WasLocalDatabaseReferencesEmpty": true
}